coingate_api
