Metadata-Version: 2.1
Name: coingate-api
Version: 0.1.5
Summary: SDK of CoinGate API for Python 3+
Home-page: https://github.com/Sociumnet/coingate-api-python
Author: Alex Shinkevich aka alexshin
Author-email: alex.shinkevich@gmail.com
License: Apache License version 2
Download-URL: https://github.com/Sociumnet/coingate-api-python/archive/v0.1.5.tar.gz
Keywords: coingate coingate-api payment merchant
Platform: UNKNOWN
Classifier: Development Status :: 5 - Production/Stable
Classifier: Programming Language :: Python :: 3
Classifier: Programming Language :: Python :: 3.5
Classifier: Programming Language :: Python :: 3.6
Classifier: Programming Language :: Python :: 3.7
Classifier: Operating System :: OS Independent
